LICENSE.md
MANIFEST.in
README.rst
setup.py
ovp_users/.coverage
ovp_users/.gitignore
ovp_users/__init__.py
ovp_users/admin.py
ovp_users/apps.py
ovp_users/emails.py
ovp_users/helpers.py
ovp_users/urls.py
ovp_users/validators.py
ovp_users.egg-info/PKG-INFO
ovp_users.egg-info/SOURCES.txt
ovp_users.egg-info/dependency_links.txt
ovp_users.egg-info/not-zip-safe
ovp_users.egg-info/requires.txt
ovp_users.egg-info/top_level.txt
ovp_users/__pycache__/__init__.cpython-35.pyc
ovp_users/__pycache__/admin.cpython-35.pyc
ovp_users/__pycache__/apps.cpython-35.pyc
ovp_users/__pycache__/emails.cpython-35.pyc
ovp_users/__pycache__/helpers.cpython-35.pyc
ovp_users/__pycache__/messages.cpython-35.pyc
ovp_users/__pycache__/models.cpython-35.pyc
ovp_users/__pycache__/permissions.cpython-35.pyc
ovp_users/__pycache__/recover_password.cpython-35.pyc
ovp_users/__pycache__/serializers.cpython-35.pyc
ovp_users/__pycache__/urls.cpython-35.pyc
ovp_users/__pycache__/validators.cpython-35.pyc
ovp_users/__pycache__/views.cpython-35.pyc
ovp_users/migrations/0001_initial.py
ovp_users/migrations/0002_auto_20160907_2116.py
ovp_users/migrations/0003_auto_20160907_2123.py
ovp_users/migrations/0004_passwordrecoverytoken.py
ovp_users/migrations/0005_passwordrecoverytoken_created_date.py
ovp_users/migrations/0006_auto_20161005_1651.py
ovp_users/migrations/0007_auto_20161005_1741.py
ovp_users/migrations/0008_auto_20161007_2052.py
ovp_users/migrations/0009_user_phone.py
ovp_users/migrations/0010_user_avatar.py
ovp_users/migrations/0011_auto_20170111_1633.py
ovp_users/migrations/0011_auto_20170112_1417.py
ovp_users/migrations/0012_merge_20170112_2144.py
ovp_users/migrations/0013_auto_20170208_2118.py
ovp_users/migrations/0014_user_locale.py
ovp_users/migrations/0015_userprofile.py
ovp_users/migrations/0016_auto_20170216_1930.py
ovp_users/migrations/0017_userprofile_causes.py
ovp_users/migrations/0018_user_uuid.py
ovp_users/migrations/0019_userprofile_public.py
ovp_users/migrations/0020_generate_user_uuids.py
ovp_users/migrations/0021_user_uuid_now_unique.py
ovp_users/migrations/0022_auto_20170222_2359.py
ovp_users/migrations/0023_auto_20170224_1829.py
ovp_users/migrations/0024_user_public.py
