Metadata-Version: 1.1
Name: ovp-users
Version: 1.1.8
Summary: This module has core functionality for ovp users, such as authentication, user management password recovery and registration
Home-page: https://github.com/OpenVolunteeringPlatform/ovp-users
Author: Atados
Author-email: arroyo@atados.com.br
License: AGPL
Download-URL: https://github.com/OpenVolunteeringPlatform/ovp-users/tarball/1.1.8
Platform: UNKNOWN
